{
	"grammar_name" : "big shapes Time Grammar", 
	"seed" : -1, 
	"framerate" : 30.0,
	"bbox" : [-2200.0, -2200.0, 2200.0, 2200.0],
	"dry_run" : false,

	"rules" : [
		{ 
			"rule_name" : "init_1",
			"matching_tags" : [],
			"produced_tags" : ["a"],
			"operator" : "time_init",
			"parameters" : [8.0, 1.0],
			"init_value" : ""
		}, 

		//================================ TIME RULES ================================

		{ 	
			"rule_name" : "time_rule_1",
			"matching_tags" : ["a"],
			"produced_tags" : ["b","c","d","e","spr1","inv_spr1","spr2","inv_spr2","spr3","inv_spr3","spr4","inv_spr4"],
			"operator" : "time_slice",
			"parameters" : [0.125,0.125,0.125,0.125,0.0625,0.0625,0.0625,0.0625,0.0625,0.0625,0.0625,0.0625], //b:1s,c:1s,d:1s,e:1s
			"init_value" : ""
		},

		{ 	
			"rule_name" : "time_rule_swaps",
			"matching_tags" : ["a"],
			"produced_tags" : ["crc1","crc2","crc3","crc4","crc1","crc2","crc3","crc4"],
			"operator" : "time_slice",
			"parameters" : [0.125,0.125,0.125,0.125,0.125,0.125,0.125,0.125], //b:1s,c:1s,d:1s,e:1s
			"init_value" : "circ2"
		},

		{ 	
			"rule_name" : "time_rule_swaps",
			"matching_tags" : ["a"],
			"produced_tags" : ["crc1","crc2","crc3","crc4","crc1","crc2","crc3","crc4"],
			"operator" : "time_slice",
			"parameters" : [0.125,0.125,0.125,0.125,0.125,0.125,0.125,0.125], //b:1s,c:1s,d:1s,e:1s
			"init_value" : "circ1"
		},

		{ 	
			"rule_name" : "time_rule_swaps",
			"matching_tags" : ["a"],
			"produced_tags" : ["swp1","inv_swp1","swp1","inv_swp1","swp1","inv_swp1","swp1","inv_swp1"],
			"operator" : "time_slice",
			"parameters" : [0.125,0.125,0.125,0.125,0.125,0.125,0.125,0.125], //b:1s,c:1s,d:1s,e:1s
			"init_value" : "swap1"
		},

		{ 	
			"rule_name" : "time_rule_swaps",
			"matching_tags" : ["a"],
			"produced_tags" : ["swp1","inv_swp1","swp1","inv_swp1","swp1","inv_swp1","swp1","inv_swp1"],
			"operator" : "time_slice",
			"parameters" : [0.125,0.125,0.125,0.125,0.125,0.125,0.125,0.125], //b:1s,c:1s,d:1s,e:1s
			"init_value" : "swap2"
		},

		{ 	
			"rule_name" : "time_rule_swaps",
			"matching_tags" : ["a"],
			"produced_tags" : ["swp1","inv_swp1","swp1","inv_swp1","swp1","inv_swp1","swp1","inv_swp1"],
			"operator" : "time_slice",
			"parameters" : [0.125,0.125,0.125,0.125,0.125,0.125,0.125,0.125], //b:1s,c:1s,d:1s,e:1s
			"init_value" : "swap3"
		},

		{ 	
			"rule_name" : "time_rule_swaps",
			"matching_tags" : ["a"],
			"produced_tags" : ["swp1","inv_swp1","swp1","inv_swp1","swp1","inv_swp1","swp1","inv_swp1"],
			"operator" : "time_slice",
			"parameters" : [0.125,0.125,0.125,0.125,0.125,0.125,0.125,0.125], //b:1s,c:1s,d:1s,e:1s
			"init_value" : "swap4"
		},

		{ 	
			"rule_name" : "time_rule_rots",
			"matching_tags" : ["a"],
			"produced_tags" : ["rot1","rot2","rot3","rot4"],
			"operator" : "time_slice",
			"parameters" : [0.25,0.25,0.25,0.25], //b:1s,c:1s,d:1s,e:1s
			"init_value" : "bb1"
		},

		{ 	
			"rule_name" : "time_rule_rots",
			"matching_tags" : ["a"],
			"produced_tags" : ["rest1","tic1","rest2","tic2","rest3","tic3","rest4","tic4","rest5","inv_tic1","rest6","inv_tic2","rest7","inv_tic3","rest8","inv_tic4"],
			"operator" : "time_slice",
			"parameters" : [0.1125,0.0125,0.1125,0.0125,0.1125,0.0125,0.1125,0.0125,0.1125,0.0125,0.1125,0.0125,0.1125,0.0125,0.1125,0.0125], //b:1s,c:1s,d:1s,e:1s
			"init_value" : "cl1"
		},

		{ 	
			"rule_name" : "time_rule_rots",
			"matching_tags" : ["a"],
			"produced_tags" : ["rest1","tic1","rest2","tic2","rest3","tic3","rest4","tic4","rest5","inv_tic1","rest6","inv_tic2","rest7","inv_tic3","rest8","inv_tic4"],
			"operator" : "time_slice",
			"parameters" : [0.1125,0.0125,0.1125,0.0125,0.1125,0.0125,0.1125,0.0125,0.1125,0.0125,0.1125,0.0125,0.1125,0.0125,0.1125,0.0125], //b:1s,c:1s,d:1s,e:1s
			"init_value" : "secscl1"
		},

		{ 	
			"rule_name" : "time_rule_rots",
			"matching_tags" : ["a"],
			"produced_tags" : ["mv1","mv2","mv3","mv4","inv_mv1","inv_mv2","inv_mv3","inv_mv4"],
			"operator" : "time_slice",
			"parameters" : [0.125,0.125,0.125,0.125,0.125,0.125,0.125,0.125], //b:1s,c:1s,d:1s,e:1s
			"init_value" : "rtr1"
		},

		{ 	
			"rule_name" : "time_rule_rots",
			"matching_tags" : ["a"],
			"produced_tags" : ["mf1","mf2","mf3","mf4","inv_mf1","inv_mf2","inv_mf3","inv_mf4"],
			"operator" : "time_slice",
			"parameters" : [0.125,0.125,0.125,0.125,0.125,0.125,0.125,0.125], //b:1s,c:1s,d:1s,e:1s
			"init_value" : "fus1"
		},

		{ 	
			"rule_name" : "time_rule_rots",
			"matching_tags" : ["a"],
			"produced_tags" : ["mf1","mf2","mf3","mf4","inv_mf1","inv_mf2","inv_mf3","inv_mf4"],
			"operator" : "time_slice",
			"parameters" : [0.125,0.125,0.125,0.125,0.125,0.125,0.125,0.125], //b:1s,c:1s,d:1s,e:1s
			"init_value" : "fus2"
		},		

		{ 	
			"rule_name" : "time_rule_rots",
			"matching_tags" : ["a"],
			"produced_tags" : ["mf1","mf2","mf3","mf4","inv_mf1","inv_mf2","inv_mf3","inv_mf4"],
			"operator" : "time_slice",
			"parameters" : [0.125,0.125,0.125,0.125,0.125,0.125,0.125,0.125], //b:1s,c:1s,d:1s,e:1s
			"init_value" : "fus3"
		},

		{ 	
			"rule_name" : "time_rule_rots",
			"matching_tags" : ["a"],
			"produced_tags" : ["mf1","mf2","mf3","mf4","inv_mf1","inv_mf2","inv_mf3","inv_mf4"],
			"operator" : "time_slice",
			"parameters" : [0.125,0.125,0.125,0.125,0.125,0.125,0.125,0.125], //b:1s,c:1s,d:1s,e:1s
			"init_value" : "fus4"
		},

		{ 	
			"rule_name" : "time_rule_rots",
			"matching_tags" : ["a"],
			"produced_tags" : ["rotr1","rotr2"],
			"operator" : "time_slice",
			"parameters" : [0.5,0.5], //b:1s,c:1s,d:1s,e:1s
			"init_value" : "sg1"
		},

		{ 	
			"rule_name" : "time_rule_rots",
			"matching_tags" : ["a"],
			"produced_tags" : ["scale1","inv_scale1"],
			"operator" : "time_slice",
			"parameters" : [0.5,0.5], //b:1s,c:1s,d:1s,e:1s
			"init_value" : "ll1"
		},

		{ 	
			"rule_name" : "time_rule_1",
			"matching_tags" : ["a"],
			"produced_tags" : ["b1","inv_b1","rest"],
			"operator" : "time_slice",
			"parameters" : [0.25,0.25,0.5], //b1:2s,c1:2s
			"init_value" : "a5"
		},

		{ 	
			"rule_name" : "time_rule_1",
			"matching_tags" : ["a"],
			"produced_tags" : ["b2","inv_b2","b3","inv_b3","sctr1","inv_sctr1","sctr2","inv_sctr2"],
			"operator" : "time_slice",
			"parameters" : [0.125,0.125,0.125,0.125,0.5], //b1:2s,c1:2s
			"init_value" : "a12"
		},

		{ 	
			"rule_name" : "time_rule_1",
			"matching_tags" : ["a"],
			"produced_tags" : ["r","sctr1","r","inv_sctr1","r","sctr2","r","inv_sctr2"],
			"operator" : "time_slice",
			"parameters" : [0.125,0.125,0.125,0.125,0.125,0.125,0.125,0.125], //b1:2s,c1:2s
			"init_value" : "scltrs1"
		},

		{ 	
			"rule_name" : "time_rule_2",
			"matching_tags" : ["b"],
			"produced_tags" : ["f","g","h","i"],
			"operator" : "time_slice",
			"parameters" : [0.25,0.25,0.25,0.25], //0.25s,0.25s,0.25s,0.25s
			"init_value" : ""
		},

		{ 	
			"rule_name" : "time_rule_3",
			"matching_tags" : ["d"],
			"produced_tags" : ["inv_i","inv_h","inv_g","inv_f"],
			"operator" : "time_slice",
			"parameters" : [0.25,0.25,0.25,0.25], //0.25s,0.25s,0.25s,0.25s
			"init_value" : ""
		},

		{ 	
			"rule_name" : "time_rule_3",
			"matching_tags" : ["d"],
			"produced_tags" : ["j","inv_j","k","inv_k","l"],
			"operator" : "time_slice",
			"parameters" : [0.125,0.125,0.125,0.125,0.5], //0.25s,0.25s,0.25s,0.25s
			"init_value" : "a10"
		},

		{ 	
			"rule_name" : "time_rule_4",
			"matching_tags" : ["c"],
			"produced_tags" : ["o","inv_o","p","inv_p","q","inv_q"],
			"operator" : "time_slice",
			"parameters" : [0.25,0.125,0.125,0.125,0.125,0.25], //0.25s,0.25s,0.25s,0.25s
			"init_value" : ""
		},

		{ 	
			"rule_name" : "time_rule_4",
			"matching_tags" : ["c"],
			"produced_tags" : ["r","s"],
			"operator" : "time_slice",
			"parameters" : [0.5,0.5], //0.25s,0.25s,0.25s,0.25s
			"init_value" : "a11"
		},

		{ 	
			"rule_name" : "time_rule_2",
			"matching_tags" : ["b"],
			"produced_tags" : ["b4","b5"],
			"operator" : "time_slice",
			"parameters" : [0.5,0.5], //0.25s,0.25s,0.25s,0.25s
			"init_value" : "a13"
		},

		{ 	
			"rule_name" : "time_rule_2",
			"matching_tags" : ["b"],
			"produced_tags" : ["b6","b7"],
			"operator" : "time_slice",
			"parameters" : [0.5,0.5], //0.25s,0.25s,0.25s,0.25s
			"init_value" : "a14"
		},

		{ 	
			"rule_name" : "time_rule_2",
			"matching_tags" : ["b"],
			"produced_tags" : ["b8","b9"],
			"operator" : "time_slice",
			"parameters" : [0.5,0.5], //0.25s,0.25s,0.25s,0.25s
			"init_value" : "a15"
		},

		{ 	
			"rule_name" : "time_rule_2",
			"matching_tags" : ["d"],
			"produced_tags" : ["d4","d5"],
			"operator" : "time_slice",
			"parameters" : [0.5,0.5], //0.25s,0.25s,0.25s,0.25s
			"init_value" : "a13"
		},

		{ 	
			"rule_name" : "time_rule_2",
			"matching_tags" : ["d"],
			"produced_tags" : ["d6","d7"],
			"operator" : "time_slice",
			"parameters" : [0.5,0.5], //0.25s,0.25s,0.25s,0.25s
			"init_value" : "a14"
		},

		{ 	
			"rule_name" : "time_rule_2",
			"matching_tags" : ["d"],
			"produced_tags" : ["d8","d9"],
			"operator" : "time_slice",
			"parameters" : [0.5,0.5], //0.25s,0.25s,0.25s,0.25s
			"init_value" : "a15"
		},

		{ 	
			"rule_name" : "time_rule_2",
			"matching_tags" : ["b4"],
			"produced_tags" : ["b4_1","b4_2","b4_3"],
			"operator" : "time_slice",
			"parameters" : [0.5,0.25,0.25], //0.25s,0.25s,0.25s,0.25s
			"init_value" : "a13"
		},

		{ 	
			"rule_name" : "time_rule_2",
			"matching_tags" : ["b6"],
			"produced_tags" : ["b6_1","b6_2","b6_3"],
			"operator" : "time_slice",
			"parameters" : [0.25,0.5,0.25], //0.25s,0.25s,0.25s,0.25s
			"init_value" : "a14"
		},
		{ 	
			"rule_name" : "time_rule_2",
			"matching_tags" : ["b8"],
			"produced_tags" : ["b8_1","b8_2","b8_3"],
			"operator" : "time_slice",
			"parameters" : [0.25,0.25,0.5], //0.25s,0.25s,0.25s,0.25s
			"init_value" : "a15"
		},

		{ 	
			"rule_name" : "time_rule_2",
			"matching_tags" : ["d4"],
			"produced_tags" : ["inv_b4_1","d4_2","d4_3"],
			"operator" : "time_slice",
			"parameters" : [0.5,0.25,0.25], //0.25s,0.25s,0.25s,0.25s
			"init_value" : "a13"
		},
		{ 	
			"rule_name" : "time_rule_2",
			"matching_tags" : ["d6"],
			"produced_tags" : ["d6_1","inv_b6_2","d6_3"],
			"operator" : "time_slice",
			"parameters" : [0.25,0.5,0.25], //0.25s,0.25s,0.25s,0.25s
			"init_value" : "a14"
		},
		{ 	
			"rule_name" : "time_rule_2",
			"matching_tags" : ["d8"],
			"produced_tags" : ["d8_1","d8_2","inv_b8_3"],
			"operator" : "time_slice",
			"parameters" : [0.25,0.25,0.5], //0.25s,0.25s,0.25s,0.25s
			"init_value" : "a15"
		},

		//================================ END TIME RULES ================================
		//================================ SPACE RULES ================================

		{ 	
			"rule_name" : "space_rule_cs1",
			"matching_tags" : ["a1"],
			"produced_tags" : ["cs1_b1"],
			"operator" : "translation",
			"parameters" : [0.0, 0.0, 10.0, 0.0],
			"init_value" : "f"
		},

		{ 	
			"rule_name" : "space_rule_cs2",
			"matching_tags" : ["a2"],
			"produced_tags" : ["cs2_b2"],
			"operator" : "translation",
			"parameters" : [0.0, 0.0, 10.0, 0.0],
			"init_value" : "g"
		},

		{ 	
			"rule_name" : "space_rule_cs3",
			"matching_tags" : ["a3"],
			"produced_tags" : ["cls3_b3"],
			"operator" : "translation",
			"parameters" : [0.0, 0.0, 10.0, 0.0],
			"init_value" : "h"
		},

		{ 	
			"rule_name" : "space_rule_cs4",
			"matching_tags" : ["a4"],
			"produced_tags" : ["cs4_b4"],
			"operator" : "translation",
			"parameters" : [0.0, 0.0, 10.0, 0.0],
			"init_value" : "i"
		},

		{ 	
			"rule_name" : "space_rule_cs5",
			"matching_tags" : ["a5"],
			"produced_tags" : ["cs5_e1"],
			"operator" : "translation",
			"parameters" : [0.0, -10.0, 0.0, 0.0],
			"init_value" : "b1"
		},

		{ 	
			"rule_name" : "space_rule_cs5",
			"matching_tags" : ["a6"],
			"produced_tags" : ["cs5_e1"],
			"operator" : "translation",
			"parameters" : [0.0, -20.0, 0.0, 0.0],
			"init_value" : "i"
		},

		{ 	
			"rule_name" : "space_rule_cs5",
			"matching_tags" : ["a10"],
			"produced_tags" : ["cs5_e1"],
			"operator" : "translation",
			"parameters" : [0.0, 0.0, 2.0, 0.0],
			"init_value" : "j"
		},

		{ 	
			"rule_name" : "space_rule_cs5",
			"matching_tags" : ["a10"],
			"produced_tags" : ["cs5_e1"],
			"operator" : "translation",
			"parameters" : [0.0, 0.0, 2.0, 0.0],
			"init_value" : "k"
		},

		{ 	
			"rule_name" : "space_rule_cs5",
			"matching_tags" : ["a7"],
			"produced_tags" : ["cs5_e1"],
			"operator" : "translation",
			"parameters" : [0.0, 3.0, 0.0, 0.0],
			"init_value" : "o"
		},		

		{ 	
			"rule_name" : "space_rule_cs5",
			"matching_tags" : ["a8"],
			"produced_tags" : ["cs5_e1"],
			"operator" : "translation",
			"parameters" : [0.0, -3.0, 0.0, 0.0],
			"init_value" : "p"
		},		

		{ 	
			"rule_name" : "space_rule_cs5",
			"matching_tags" : ["a9"],
			"produced_tags" : ["cs5_e1"],
			"operator" : "translation",
			"parameters" : [0.0, 3.0, 0.0, 0.0],
			"init_value" : "q"
		},

		{ 	
			"rule_name" : "space_rule_cs5",
			"matching_tags" : ["a11"],
			"produced_tags" : ["cs5_e1"],
			"operator" : "translation",
			"parameters" : [0.0, -15.0, 0.0, 0.0],
			"init_value" : "r"
		},

		{ 	
			"rule_name" : "space_rule_cs5",
			"matching_tags" : ["a11"],
			"produced_tags" : ["cs5_e1"],
			"operator" : "translation",
			"parameters" : [0.0, 15.0, 0.0, 0.0],
			"init_value" : "e"
		},

		{ 	
			"rule_name" : "space_rule_cs5",
			"matching_tags" : ["a12"],
			"produced_tags" : ["cs5_e1"],
			"operator" : "translation",
			"parameters" : [0.0, 20.0, -20.0, 0.0],
			"init_value" : "b2"
		},

		{ 	
			"rule_name" : "space_rule_cs5",
			"matching_tags" : ["a12"],
			"produced_tags" : ["cs5_e1"],
			"operator" : "translation",
			"parameters" : [0.0, 20.0, -20.0, 0.0],
			"init_value" : "b3"
		},

		{ 	
			"rule_name" : "space_rule_cs5",
			"matching_tags" : ["a13"],
			"produced_tags" : ["cs5_e1"],
			"operator" : "translation",
			"parameters" : [0.0, 0.0, -5.0, 0.0],
			"init_value" : "b4_1"
		},

		{ 	
			"rule_name" : "space_rule_cs5",
			"matching_tags" : ["a14"],
			"produced_tags" : ["cs5_e1"],
			"operator" : "translation",
			"parameters" : [0.0, 0.0, -5.0, 0.0],
			"init_value" : "b6_2"
		},

		{ 	
			"rule_name" : "space_rule_cs5",
			"matching_tags" : ["a15"],
			"produced_tags" : ["cs5_e1"],
			"operator" : "translation",
			"parameters" : [0.0, 0.0, -5.0, 0.0],
			"init_value" : "b8_3"
		},


		{ 	
			"rule_name" : "space_rule_cs5",
			"matching_tags" : ["a16"],
			"produced_tags" : ["cs5_e1"],
			"operator" : "translation",
			"parameters" : [0.0, 0.0, -1.0, 0.0],
			"init_value" : "i"
		},

		{ 	
			"rule_name" : "space_rule_cs5",
			"matching_tags" : ["a17"],
			"produced_tags" : ["cs5_e1"],
			"operator" : "translation",
			"parameters" : [0.0, 0.0, -1.0, 0.0],
			"init_value" : "g"
		},



		//====================== NEW ONES =======================//

		//====================== RTR =======================//

		{
				"rule_name" : "rule_rtr1",
		    	"matching_tags" : ["rtr1"], 
    			"produced_tags" : ["rototras1"],
   				"operator" : "rot_tran",
    			"parameters" : [1.0, -90.0, -10.0, 0.0, 0.05],
    			"init_value" : "mv1"
    	},

		{
				"rule_name" : "rule_rtr2",
		    	"matching_tags" : ["rtr1"], 
    			"produced_tags" : ["rototras2"],
   				"operator" : "rot_tran",
    			"parameters" : [1.0, -90.0, 0.0, 10.0, 0.05],
    			"init_value" : "mv2"
    	},

    	{
				"rule_name" : "rule_rtr3",
		    	"matching_tags" : ["rtr1"], 
    			"produced_tags" : ["rototras3"],
   				"operator" : "rot_tran",
    			"parameters" : [1.0, -90.0, 10.0, 0.0, 0.05],
    			"init_value" : "mv3"
    	},

    	{
				"rule_name" : "rule_rtr4",
		    	"matching_tags" : ["rtr1"], 
    			"produced_tags" : ["rototras4"],
   				"operator" : "rot_tran",
    			"parameters" : [1.0, -90.0, 0.0, -10.0, 0.05],
    			"init_value" : "mv4"
    	},

		//====================== BB1 =======================//

		{ 	
			"rule_name" : "space_rule1_bb1",
			"matching_tags" : ["bb1"],
			"produced_tags" : ["bb1_rot1"],
			"operator" : "rotation",
			"parameters" : [1.0, -90.0, 0.0],
			"init_value" : "rot1"
		},

		{ 	
			"rule_name" : "space_rule1_bb1",
			"matching_tags" : ["bb1"],
			"produced_tags" : ["bb1_rot1"],
			"operator" : "rotation",
			"parameters" : [1.0, -90.0, 0.0],
			"init_value" : "rot2"
		},

		{ 	
			"rule_name" : "space_rule1_bb1",
			"matching_tags" : ["bb1"],
			"produced_tags" : ["bb1_rot1"],
			"operator" : "rotation",
			"parameters" : [1.0, -90.0, 0.0],
			"init_value" : "rot3"
		},

		{ 	
			"rule_name" : "space_rule1_bb1",
			"matching_tags" : ["bb1"],
			"produced_tags" : ["bb1_rot1"],
			"operator" : "rotation",
			"parameters" : [1.0, -90.0, 0.0],
			"init_value" : "rot4"
		},		

		//====================== LL1 =======================//
		
		{ 	
			"rule_name" : "space_rule1_ll1",
			"matching_tags" : ["ll1"],
			"produced_tags" : ["ll1_sc"],
			"operator" : "scale",
			"parameters" : [1.0, 2.0, 0.0],
			"init_value" : "scale1"
		},

		//====================== sg1 =======================//
		
		{
			"rule_name" : "rule_rtr1",
	    	"matching_tags" : ["sg1"], 
			"produced_tags" : ["rototras1"],
			"operator" : "rot_tran",
			"parameters" : [1.0, -90.0, 0.0, 20.0, 0.05],
			"init_value" : "rotr1"
    	},

		{
			"rule_name" : "rule_rtr1",
	    	"matching_tags" : ["sg1"], 
			"produced_tags" : ["rototras1"],
			"operator" : "rot_tran",
			"parameters" : [1.0, -90.0, 0.0, -20.0, 0.05],
			"init_value" : "rotr2"
    	},

		//====================== cl1 =======================//
		
		{ 	
			"rule_name" : "space_rule1_cl1",
			"matching_tags" : ["cl1"],
			"produced_tags" : ["cl1_rot1"],
			"operator" : "rotation",
			"parameters" : [1.0, -90.0, 0.0],
			"init_value" : "tic1"
		},

		{ 	
			"rule_name" : "space_rule2_cl1",
			"matching_tags" : ["cl1"],
			"produced_tags" : ["cl1_rot2"],
			"operator" : "rotation",
			"parameters" : [1.0, -90.0, 0.0],
			"init_value" : "tic2"
		},

		{ 	
			"rule_name" : "space_rule3_cl1",
			"matching_tags" : ["cl1"],
			"produced_tags" : ["cl1_rot3"],
			"operator" : "rotation",
			"parameters" : [1.0, -90.0, 0.0],
			"init_value" : "tic3"
		},

		{ 	
			"rule_name" : "space_rule4_cl1",
			"matching_tags" : ["cl1"],
			"produced_tags" : ["cl1_rot4"],
			"operator" : "rotation",
			"parameters" : [1.0, -90.0, 0.0],
			"init_value" : "tic4"
		},

		//====================== pr1234 =======================//

		{ 	
			"rule_name" : "space_rule_pr1",
			"matching_tags" : ["pr1"],
			"produced_tags" : ["c_t1"],
			"operator" : "scale",
			"parameters" : [1.0, 0.2, 0.0],
			"init_value" : "spr1"
		},

		{ 	
			"rule_name" : "space_rule_pr2",
			"matching_tags" : ["pr2"],
			"produced_tags" : ["c_t1"],
			"operator" : "scale",
			"parameters" : [1.0, 0.2, 0.0],
			"init_value" : "spr2"
		},

		{ 	
			"rule_name" : "space_rule_pr3",
			"matching_tags" : ["pr3"],
			"produced_tags" : ["c_t1"],
			"operator" : "scale",
			"parameters" : [1.0, 0.2, 0.0],
			"init_value" : "spr3"
		},

		{ 	
			"rule_name" : "space_rule_pr4",
			"matching_tags" : ["pr4"],
			"produced_tags" : ["c_t1"],
			"operator" : "scale",
			"parameters" : [1.0, 0.2, 0.0],
			"init_value" : "spr4"
		},

		//====================== fus1234 =======================//

		{ 	
			"rule_name" : "space_rule_trs_fus1",
			"matching_tags" : ["fus1"],
			"produced_tags" : ["trs_fus1"],
			"operator" : "translation",
			"parameters" : [0.0, 5.0, 5.0, 0.0],
			"init_value" : "mf1"
		},

		{ 	
			"rule_name" : "space_rule_trs_fus2",
			"matching_tags" : ["fus2"],
			"produced_tags" : ["trs_fus2"],
			"operator" : "translation",
			"parameters" : [0.0, -5.0, 5.0, 0.0],
			"init_value" : "mf2"
		},

		{ 	
			"rule_name" : "space_rule_trs_fus3",
			"matching_tags" : ["fus3"],
			"produced_tags" : ["trs_fus3"],
			"operator" : "translation",
			"parameters" : [0.0, 5.0, -5.0, 0.0],
			"init_value" : "mf3"
		},

		{ 	
			"rule_name" : "space_rule_trs_fus4",
			"matching_tags" : ["fus4"],
			"produced_tags" : ["trs_fus4"],
			"operator" : "translation",
			"parameters" : [0.0, -5.0, -5.0, 0.0],
			"init_value" : "mf4"
		},

		{ 	
			"rule_name" : "space_rule_secscl1",
			"matching_tags" : ["secscl1"],
			"produced_tags" : ["secscl1_t1"],
			"operator" : "scale",
			"parameters" : [1.0, 0.8, 0.0],
			"init_value" : "tic1"
		},

		{ 	
			"rule_name" : "space_rule_secscl1",
			"matching_tags" : ["secscl1"],
			"produced_tags" : ["secscl1_t1"],
			"operator" : "scale",
			"parameters" : [1.0, 0.8, 0.0],
			"init_value" : "tic2"
		},

		{ 	
			"rule_name" : "space_rule_secscl1",
			"matching_tags" : ["secscl1"],
			"produced_tags" : ["secscl1_t1"],
			"operator" : "scale",
			"parameters" : [1.0, 0.8, 0.0],
			"init_value" : "tic3"
		},

		{ 	
			"rule_name" : "space_rule_secscl1",
			"matching_tags" : ["secscl1"],
			"produced_tags" : ["secscl1_t1"],
			"operator" : "scale",
			"parameters" : [1.0, 0.8, 0.0],
			"init_value" : "tic4"
		},

		{ 	
			"rule_name" : "space_rule_trs_swap1",
			"matching_tags" : ["swap1"],
			"produced_tags" : ["trs_fus4"],
			"operator" : "translation",
			"parameters" : [0.0, 8.0, 2.0, 0.0],
			"init_value" : "swp1"
		},

		{ 	
			"rule_name" : "space_rule_trs_swap2",
			"matching_tags" : ["swap2"],
			"produced_tags" : ["trs_fus4"],
			"operator" : "translation",
			"parameters" : [0.0, -8.0, -2.0, 0.0],
			"init_value" : "swp1"
		},

		{ 	
			"rule_name" : "space_rule_trs_swap3",
			"matching_tags" : ["swap3"],
			"produced_tags" : ["trs_fus4"],
			"operator" : "translation",
			"parameters" : [0.0, 0.0, 7.0, 0.0],
			"init_value" : "swp1"
		},

		{ 	
			"rule_name" : "space_rule_trs_swap4",
			"matching_tags" : ["swap4"],
			"produced_tags" : ["trs_fus4"],
			"operator" : "translation",
			"parameters" : [0.0, 0.0, -7.0, 0.0],
			"init_value" : "swp1"
		},

		{ 	
			"rule_name" : "space_rule_trs_circ1",
			"matching_tags" : ["circ1"],
			"produced_tags" : ["trs_fus4"],
			"operator" : "translation",
			"parameters" : [0.0, 38.0, 15.0, 0.0],
			"init_value" : "crc1"
		},

		{ 	
			"rule_name" : "space_rule_trs_circ1",
			"matching_tags" : ["circ1"],
			"produced_tags" : ["trs_fus4"],
			"operator" : "translation",
			"parameters" : [0.0, 0.0, -27.0, 0.0],
			"init_value" : "crc2"
		},

		{ 	
			"rule_name" : "space_rule_trs_circ1",
			"matching_tags" : ["circ1"],
			"produced_tags" : ["trs_fus4"],
			"operator" : "translation",
			"parameters" : [0.0, -38.0, -15.0, 0.0],
			"init_value" : "crc3"
		},

		{ 	
			"rule_name" : "space_rule_trs_circ1",
			"matching_tags" : ["circ1"],
			"produced_tags" : ["trs_fus4"],
			"operator" : "translation",
			"parameters" : [0.0, 0.0, 27.0, 0.0],
			"init_value" : "crc4"
		},

		{ 	
			"rule_name" : "space_rule_trs_circ2",
			"matching_tags" : ["circ2"],
			"produced_tags" : ["trs_fus4"],
			"operator" : "translation",
			"parameters" : [0.0, -38.0, -15.0, 0.0],
			"init_value" : "crc1"
		},

		{ 	
			"rule_name" : "space_rule_trs_circ2",
			"matching_tags" : ["circ2"],
			"produced_tags" : ["trs_fus4"],
			"operator" : "translation",
			"parameters" : [0.0, 0.0, 27.0, 0.0],
			"init_value" : "crc2"
		},
		
		{ 	
			"rule_name" : "space_rule_trs_circ2",
			"matching_tags" : ["circ2"],
			"produced_tags" : ["trs_fus4"],
			"operator" : "translation",
			"parameters" : [0.0, 38.0, 15.0, 0.0],
			"init_value" : "crc3"
		},

		{ 	
			"rule_name" : "space_rule_trs_circ2",
			"matching_tags" : ["circ2"],
			"produced_tags" : ["trs_fus4"],
			"operator" : "translation",
			"parameters" : [0.0, 0.0, -27.0, 0.0],
			"init_value" : "crc4"
		},


		{ 	
			"rule_name" : "space_rule_scltrs1",
			"matching_tags" : ["scltrs1"],
			"produced_tags" : ["up_scltrs1"],
			"operator" : "scale_tran",
			"parameters" : [1.0, 0.5, 0.0, -20.0, 0.0],
			"init_value" : "sctr1"
		},

		{ 	
			"rule_name" : "space_rule_scltrs1",
			"matching_tags" : ["scltrs1"],
			"produced_tags" : ["down_scltrs1"],
			"operator" : "scale_tran",
			"parameters" : [1.0, 0.5, 0.0, 20.0, 0.0],
			"init_value" : "sctr2"
		}



	]
}
